
{
  "placeholderImages": [
    {
      "id": "banner-1",
      "description": "Tech Sale Banner",
      "imageUrl": "https://picsum.photos/seed/tech1/800/400",
      "imageHint": "technology electronics"
    },
    {
      "id": "banner-2",
      "description": "Fashion Sale Banner",
      "imageUrl": "https://picsum.photos/seed/fashion1/800/400",
      "imageHint": "fashion clothing"
    },
    {
      "id": "prod-1",
      "description": "Wireless Headphones",
      "imageUrl": "https://picsum.photos/seed/headphones/400/400",
      "imageHint": "headphones gadget"
    },
    {
      "id": "prod-2",
      "description": "Smart Watch",
      "imageUrl": "https://picsum.photos/seed/watch/400/400",
      "imageHint": "smartwatch gadget"
    },
    {
      "id": "prod-3",
      "description": "Running Shoes",
      "imageUrl": "https://picsum.photos/seed/shoes/400/400",
      "imageHint": "sneakers sport"
    },
    {
      "id": "prod-4",
      "description": "Designer T-Shirt",
      "imageUrl": "https://picsum.photos/seed/shirt/400/400",
      "imageHint": "tshirt fashion"
    },
    {
      "id": "prod-5",
      "description": "Coffee Maker",
      "imageUrl": "https://picsum.photos/seed/coffee/400/400",
      "imageHint": "coffee machine"
    },
    {
      "id": "prod-6",
      "description": "Leather Backpack",
      "imageUrl": "https://picsum.photos/seed/bag/400/400",
      "imageHint": "backpack accessories"
    },
    {
      "id": "prod-hoodie",
      "description": "BRTWL Boxy Hoodie",
      "imageUrl": "https://picsum.photos/seed/hoodie/400/400",
      "imageHint": "hoodie fashion"
    }
  ]
}
